{"file":"_courseSlug_-BRcWcs32.js","mappings":";;;;;;;;;;;;;;;;;;;;;;;;;;;;;;;;AAAA,QAAA,OAAAA,eAAAC,WACO,EAAA,OAAM,kBAAiB,GAD9B,MAAA,CAAA,uDAAAC,cAKO,OAAK,2CAA2C;;;;;;;;;ACG1C,MAAA,YAAY,CAAC,eAAwC;AAC1D,QAAA,EAAE,QAAQ,IAAI,WAAW;AAE/B,QAAM,QAAQ,QAAQ,UAAU,CAACC,YAAWA,QAAO,eAAe,UAAU;AACtE,QAAA,SAAS,QAAQ,KAAK;AAC5B,QAAM,aAAa,SAAS,IAAI,OAAO,QAAQ,QAAQ,CAAC;AAClD,QAAA,aAAa,SAAS,QAAQ,SAAS,IAAI,OAAO,QAAQ,QAAQ,CAAC;AAClE,SAAA,EAAE,QAAQ,YAAY,WAAW;AAC1C;;;;;AC6EA,UAAM,QAAQ,SAAS;AACjB,UAAA,aAAa,MAAM,OAAO;AAChC,UAAM,EAAE,QAAQ,YAAY,WAAW,IAAI,UAAU,UAAU;AAW/D,UAAM,KAAK;AAEL,UAAA,OAAO,IAAI,EAAE;AACb,UAAA,YAAY,IAAI,KAAK;;;;;;;;;;;;;;;;;;;;;;;;;;;;;;;;;;;;;;;;;;;;;;;;;;;;;;;;;;;;;;;;;;;;;;;;;;;;;;;;;;;;;;;;;;;;;;;;;;;;;;;;;;;;;;;;;;;;;;;;;;;;;;;;;;;;;;;;;;;;;;;;;;;;;;;;;;;;;;;;;;;;;;;;;;;;;;;;;;;;;;;;;;;;;;;;;;;;;;;;;;;;;;;;;;;;;;;;;;;;;;;;;;;;;;;;;;;;;;;;;;;;;;;","names":["_ssrRenderAttrs","_mergeProps","_ssrRenderAttr","course"],"sources":["../../../../components/VideoPlayer.vue","../../../../composables/useCourse.ts","../../../../pages/course/[courseSlug].vue"],"sourcesContent":["<template>\r\n  <div class=\"video-container\">\r\n    <iframe\r\n      width=\"100%\"\r\n      height=\"100%\"\r\n      :src=\"'https://www.youtube.com/embed/zmq2zu-UsRk'\"\r\n      title=\"YouTube video player\"\r\n      frameborder=\"0\"\r\n      allow=\"accelerometer; autoplay; clipboard-write; encrypted-media; gyroscope; picture-in-picture; web-share\"\r\n      allowfullscreen\r\n    ></iframe>\r\n  </div>\r\n</template>\r\n\r\n<script setup lang=\"ts\"></script>\r\n\r\n<style scoped>\r\n.video-container {\r\n  position: relative;\r\n  padding-bottom: 56.25%;\r\n  padding-top: 30px;\r\n  height: 0;\r\n  overflow: hidden;\r\n}\r\n\r\n.video-container iframe,\r\n.video-container object,\r\n.video-container embed {\r\n  position: absolute;\r\n  top: 0;\r\n  left: 0;\r\n  width: 100%;\r\n  height: 100%;\r\n}\r\n</style>","import type { CourseWithPath } from '~/types/course';\r\n\r\ninterface UseCourseReturn {\r\n  course: Maybe<CourseWithPath>;\r\n  prevCourse: Maybe<CourseWithPath>;\r\n  nextCourse: Maybe<CourseWithPath>;\r\n}\r\n\r\nexport const useCourse = (courseSlug: string): UseCourseReturn => {\r\n  const { courses } = useCourses();\r\n  // const course = courses.find((course) => course.courseSlug === courseSlug);\r\n  const index = courses.findIndex((course) => course.courseSlug === courseSlug);\r\n  const course = courses[index];\r\n  const prevCourse = index <= 0 ? null : courses[index - 1];\r\n  const nextCourse = index >= courses.length - 1 ? null : courses[index + 1];\r\n  return { course, prevCourse, nextCourse };\r\n};","<template>\r\n  <AppCard>\r\n    <template #header>\r\n      <div class=\"text-h5 text-weight-medium\">{{ course?.title }}</div>\r\n      <div class=\"flex q-gutter-x-sm items-center q-mt-sm text-grey-8\">\r\n        <span class=\"flex items-center\">\r\n          <q-icon name=\"star\" size=\"16px\" color=\"orange\" />\r\n          <span>{{ course?.rating }}</span>\r\n        </span>\r\n        <span> {{ course?.reviewsCount }}개의 수강평 </span>\r\n        <span>&middot;</span>\r\n        <span>{{ course?.studentCount }}명의 수강생</span>\r\n        <q-space />\r\n        <a class=\"text-bold\" :href=\"course?.reviewsUrl\" target=\"_blank\">\r\n          수강평 보기\r\n        </a>\r\n      </div>\r\n    </template>\r\n    <div class=\"q-mb-md\">\r\n      <VideoPlayer :src=\"course?.video\" />\r\n    </div>\r\n    <div class=\"row q-col-gutter-md\">\r\n      <div class=\"col-6\">\r\n        <q-btn\r\n          label=\"인프런에서 수강하기\"\r\n          unelevated\r\n          class=\"full-width\"\r\n          color=\"primary\"\r\n          :href=\"course?.inflearnUrl\"\r\n          target=\"_blank\"\r\n        />\r\n      </div>\r\n      <div class=\"col-6\">\r\n        <q-btn\r\n          label=\"짐코딩 클럽에서 수강하기\"\r\n          unelevated\r\n          class=\"full-width\"\r\n          color=\"red\"\r\n          :href=\"course?.gymcodingUrl\"\r\n          target=\"_blank\"\r\n        />\r\n      </div>\r\n    </div>\r\n    <p class=\"q-mt-lg text-grey-8\">{{ course?.content }}</p>\r\n    <q-separator class=\"q-mb-lg\" />\r\n    <q-form class=\"q-gutter-y-md\">\r\n      <q-btn\r\n        label=\"수강완료\"\r\n        class=\"full-width\"\r\n        color=\"green\"\r\n        unelevated\r\n        :outline=\"completed ? false : true\"\r\n        :icon=\"completed ? 'check' : undefined\"\r\n        @click=\"completed = !completed\"\r\n      />\r\n      <q-input\r\n        v-model=\"memo\"\r\n        type=\"textarea\"\r\n        outlined\r\n        dense\r\n        placeholder=\"메모를 작성해주세요.\"\r\n        rows=\"3\"\r\n\t\t\t\tautogrow\r\n      />\r\n    </q-form>\r\n    <template #footer>\r\n      <q-btn\r\n        v-if=\"prevCourse\"\r\n        label=\"이전 강의\"\r\n        color=\"primary\"\r\n        unelevated\r\n        :to=\"prevCourse.path\"\r\n      />\r\n      <q-btn\r\n        label=\"쿼리 추가\"\r\n        color=\"dark\"\r\n        unelevated\r\n        :to=\"{ path: $route.path, query: { timestamp: Date.now() } }\"\r\n      />\r\n      <q-space />\r\n      <q-btn\r\n        v-if=\"nextCourse\"\r\n        label=\"다음 강의\"\r\n        color=\"primary\"\r\n        unelevated\r\n        :to=\"nextCourse.path\"\r\n      />\r\n    </template>\r\n  </AppCard>\r\n</template>\r\n\r\n<script setup lang=\"ts\">\r\n\r\nconst route = useRoute();\r\nconst courseSlug = route.params.courseSlug as string;\r\nconst { course, prevCourse, nextCourse } = useCourse(courseSlug);\r\n// console.log('[courseSlug].vue 컴포넌트 setup hooks');\r\n// const title = ref('');\r\ndefinePageMeta({\r\n  key: (route) => route.fullPath,\r\n  // title: title.value, // 이렇게 하면 오류가 발생합니다.\r\n  title: 'My home page',\r\n  pageType: '',\r\n  keepalive: true,\r\n});\r\n\r\nroute.meta.pageType\r\n\r\nconst memo = ref('');\r\nconst completed = ref(false);\r\n</script>\r\n\r\n<style scoped></style>\r\n"],"version":3}